autograd/__init__.py
autograd/builtins.py
autograd/core.py
autograd/differential_operators.py
autograd/extend.py
autograd/test_util.py
autograd/tracer.py
autograd/util.py
autograd/wrap_util.py
autograd/misc/__init__.py
autograd/misc/fixed_points.py
autograd/misc/flatten.py
autograd/misc/optimizers.py
autograd/misc/tracers.py
autograd/numpy/__init__.py
autograd/numpy/fft.py
autograd/numpy/linalg.py
autograd/numpy/numpy_boxes.py
autograd/numpy/numpy_jvps.py
autograd/numpy/numpy_vjps.py
autograd/numpy/numpy_vspaces.py
autograd/numpy/numpy_wrapper.py
autograd/numpy/random.py
autograd/scipy/__init__.py
autograd/scipy/integrate.py
autograd/scipy/linalg.py
autograd/scipy/misc.py
autograd/scipy/signal.py
autograd/scipy/special.py
autograd/scipy/stats/__init__.py
autograd/scipy/stats/beta.py
autograd/scipy/stats/chi2.py
autograd/scipy/stats/dirichlet.py
autograd/scipy/stats/gamma.py
autograd/scipy/stats/multivariate_normal.py
autograd/scipy/stats/norm.py
autograd/scipy/stats/poisson.py
autograd/scipy/stats/t.py
autograd_latest-1.3.dist-info/METADATA
autograd_latest-1.3.dist-info/WHEEL
autograd_latest-1.3.dist-info/license.txt
autograd_latest-1.3.dist-info/top_level.txt
autograd_latest-1.3.dist-info/RECORD
